README.rst
setup.cfg
setup.py
scripts/tcp2canopsis
tcp2canopsis/__init__.py
tcp2canopsis/connector.py
tcp2canopsis/daemon.py
tcp2canopsis/errors.py
tcp2canopsis/factory.py
tcp2canopsis.egg-info/PKG-INFO
tcp2canopsis.egg-info/SOURCES.txt
tcp2canopsis.egg-info/dependency_links.txt
tcp2canopsis.egg-info/requires.txt
tcp2canopsis.egg-info/top_level.txt