Metadata-Version: 1.1
Name: tcp2canopsis
Version: 0.3
Summary: Canopsis Connector which listen for JSON events on TCP port
Home-page: https://github.com/linkdd/tcp2canopsis
Author: David Delassus
Author-email: david.jose.delassus@gmail.com
License: MIT
Download-URL: https://github.com/linkdd/tcp2canopsis/tarball/0.2
Keywords: canopsis
Platform: UNKNOWN
